IBITNormalizer/__init__.py
IBITNormalizer/normalizer.py
IBITNormalizer/resource/Normalizer/Dic1_new.txt
IBITNormalizer/resource/Normalizer/Dic2_new.txt
IBITNormalizer/resource/Normalizer/Dic3_new.txt
IBITNormalizer/resource/Stopwords/Kharazi/Pesian_Stop_Words_List.txt
IBITNormalizer/resource/Stopwords/Mazdak/Persian_StopList.txt
IBITNormalizer/resource/Stopwords/Mojiry/PersianStopWords.txt
IBITNormalizer/resource/Stopwords/Savoy/persianST.txt
IBITNormalizer/resource/Stopwords/Taghva/non-verbal_stopwords.txt
IBITNormalizer/resource/Stopwords/Taghva/verbal_stopwords.txt
IBITNormalizer/resource/Stopwords/shokri/stop-words.txt
IBITNormalizer-1.2.8.dist-info/METADATA
IBITNormalizer-1.2.8.dist-info/WHEEL
IBITNormalizer-1.2.8.dist-info/top_level.txt
IBITNormalizer-1.2.8.dist-info/RECORD
