Metadata-Version: 2.1
Name: IBITNormalizer
Version: 1.2.8
Summary: Normalizer for Persian texts based on hazm
Author: MahdiGhaemi
Author-email: mahdighaemi123@email.com
Requires-Dist: hazm
